fhconfparser/__init__.py
fhconfparser/fhconfparser.py
fhconfparser/simpleconf.py
fhconfparser-2024.dist-info/LICENSE.md
fhconfparser-2024.dist-info/METADATA
fhconfparser-2024.dist-info/WHEEL
fhconfparser-2024.dist-info/RECORD
