Metadata-Version: 2.1
Name: fhconfparser
Version: 2024
Summary: Provides a config language independent way to read a config file.
Home-page: https://github.com/FHPythonUtils/FHConfParser
License: MIT
Author: FredHappyface
Requires-Python: >=3.8,<4.0
Classifier: Development Status :: 5 - Production/Stable
Classifier: Intended Audience :: Developers
Classifier: Intended Audience :: Education
Classifier: License :: OSI Approved :: MIT License
Classifier: Natural Language :: English
Classifier: Operating System :: OS Independent
Classifier: Programming Language :: Python :: 3
Classifier: Programming Language :: Python :: 3.8
Classifier: Programming Language :: Python :: 3.9
Classifier: Programming Language :: Python :: 3.10
Classifier: Programming Language :: Python :: 3.11
Classifier: Programming Language :: Python :: 3.12
Classifier: Programming Language :: Python :: Implementation :: CPython
Classifier: Topic :: Security
Classifier: Topic :: Software Development :: Libraries :: Python Modules
Classifier: Topic :: Utilities
Requires-Dist: attrs (>=23.2.0,<24)
Requires-Dist: tomli (>=2.0.1,<3)
Project-URL: Documentation, https://github.com/FHPythonUtils/FHConfParser/blob/master/README.md
Project-URL: Repository, https://github.com/FHPythonUtils/FHConfParser
